calamardolauncher/__init__.py
calamardolauncher/__main__.py
calamardolauncher/web/main.html
calamardolauncher/web/bootstrap/css/bootstrap-grid.css
calamardolauncher/web/bootstrap/css/bootstrap-grid.min.css
calamardolauncher/web/bootstrap/css/bootstrap-reboot.css
calamardolauncher/web/bootstrap/css/bootstrap-reboot.min.css
calamardolauncher/web/bootstrap/css/bootstrap.css
calamardolauncher/web/bootstrap/css/bootstrap.min.css
calamardolauncher/web/bootstrap/css/theme/bootstrap.css
calamardolauncher/web/bootstrap/css/theme/bootstrap.min.css
calamardolauncher/web/bootstrap/css/theme2/bootstrap.css
calamardolauncher/web/bootstrap/css/theme2/bootstrap.min.css
calamardolauncher/web/bootstrap/js/bootstrap.bundle.js
calamardolauncher/web/bootstrap/js/bootstrap.bundle.min.js
calamardolauncher/web/bootstrap/js/bootstrap.js
calamardolauncher/web/bootstrap/js/bootstrap.min.js
calamardolauncher/web/bootstrap-select/css/bootstrap-select.css
calamardolauncher/web/bootstrap-select/css/bootstrap-select.css.map
calamardolauncher/web/bootstrap-select/css/bootstrap-select.min.css
calamardolauncher/web/bootstrap-select/js/bootstrap-select.js
calamardolauncher/web/bootstrap-select/js/bootstrap-select.js.map
calamardolauncher/web/bootstrap-select/js/bootstrap-select.min.js
calamardolauncher/web/bootstrap-select/js/bootstrap-select.min.js.map
calamardolauncher/web/bootstrap4-toggle/css/bootstrap4-toggle.css
calamardolauncher/web/bootstrap4-toggle/css/bootstrap4-toggle.min.css
calamardolauncher/web/bootstrap4-toggle/js/bootstrap4-toggle.js
calamardolauncher/web/bootstrap4-toggle/js/bootstrap4-toggle.min.js
calamardolauncher/web/bootstrap4-toggle/js/bootstrap4-toggle.min.js.map
calamardolauncher/web/js/controller.js
calamardolauncher/web/js/expose.js
calamardolauncher/web/js/jquery-3.4.1.min.js
calamardolauncher/web/js/prototype.js
calamardolauncher-0.1.2.dist-info/DESCRIPTION.rst
calamardolauncher-0.1.2.dist-info/METADATA
calamardolauncher-0.1.2.dist-info/RECORD
calamardolauncher-0.1.2.dist-info/WHEEL
calamardolauncher-0.1.2.dist-info/entry_points.txt
calamardolauncher-0.1.2.dist-info/metadata.json
calamardolauncher-0.1.2.dist-info/top_level.txt
