Metadata-Version: 2.0
Name: calamardolauncher
Version: 0.1.2
Summary: Compose Calamardo's params and launches the binary to generate files.
Home-page: https://github.com/manso92/calamardolauncher
Author: Pablo Manso
Author-email: 92manso@gmail.com
License: MIT
Keywords: gui,executable
Platform: UNKNOWN
Classifier: License :: OSI Approved :: MIT License
Classifier: Programming Language :: Python
Classifier: Programming Language :: Python :: 3
Classifier: Programming Language :: Python :: 3.6
Classifier: Programming Language :: Python :: 3.7
Classifier: Operating System :: Microsoft :: Windows
Classifier: Operating System :: POSIX :: Linux
Requires-Python: >=3.6
Requires-Dist: Eel (==0.10.4)
Requires-Dist: google-api-python-client
Requires-Dist: google-auth-httplib2
Requires-Dist: google-auth-oauthlib
